README.txt
bootstrap.py
buildout.cfg
setup.py
docs/HISTORY.txt
src/xooof/__init__.py
src/xooof.schema.dev.egg-info/PKG-INFO
src/xooof.schema.dev.egg-info/SOURCES.txt
src/xooof.schema.dev.egg-info/dependency_links.txt
src/xooof.schema.dev.egg-info/entry_points.txt
src/xooof.schema.dev.egg-info/namespace_packages.txt
src/xooof.schema.dev.egg-info/not-zip-safe
src/xooof.schema.dev.egg-info/requires.txt
src/xooof.schema.dev.egg-info/top_level.txt
src/xooof/schema/__init__.py
src/xooof/schema/dev/__init__.py
src/xooof/schema/dev/catalog.xml
src/xooof/schema/dev/struct.dtd
src/xooof/schema/dev/structtopo.py
src/xooof/schema/dev/structtozschema.py