Metadata-Version: 1.0
Name: xooof.schema.dev
Version: 0.1.1
Summary: The zope schema parts of the xooof runtime development tools for python
Home-page: http://sourceforge.net/projects/xooof/
Author: Laurent Mignon
Author-email: laurent.mignon__at__softwareag.com
License: GNU Lesser General Public License
Platform: UNKNOWN
Classifier: Framework :: Plone
Classifier: Framework :: Zope2
Classifier: Framework :: Zope3
Classifier: Programming Language :: Python
Classifier: Topic :: Software Development :: Libraries :: Python Modules
